django_ckeditor_5/__init__.py
django_ckeditor_5/apps.py
django_ckeditor_5/exceptions.py
django_ckeditor_5/fields.py
django_ckeditor_5/forms.py
django_ckeditor_5/package-lock.json
django_ckeditor_5/package.json
django_ckeditor_5/permissions.py
django_ckeditor_5/signals.py
django_ckeditor_5/storage_utils.py
django_ckeditor_5/urls.py
django_ckeditor_5/validators.py
django_ckeditor_5/views.py
django_ckeditor_5/webpack.config.js
django_ckeditor_5/widgets.py
django_ckeditor_5/static/django_ckeditor_5/app.js
django_ckeditor_5/static/django_ckeditor_5/dist/bundle.js
django_ckeditor_5/static/django_ckeditor_5/dist/bundle.js.LICENSE.txt
django_ckeditor_5/static/django_ckeditor_5/dist/bundle.js.map
django_ckeditor_5/static/django_ckeditor_5/dist/styles.css
django_ckeditor_5/static/django_ckeditor_5/dist/styles.css.map
django_ckeditor_5/static/django_ckeditor_5/dist/translations/af.js
django_ckeditor_5/static/django_ckeditor_5/dist/translations/ar.js
django_ckeditor_5/static/django_ckeditor_5/dist/translations/ast.js
django_ckeditor_5/static/django_ckeditor_5/dist/translations/az.js
django_ckeditor_5/static/django_ckeditor_5/dist/translations/be.js
django_ckeditor_5/static/django_ckeditor_5/dist/translations/bg.js
django_ckeditor_5/static/django_ckeditor_5/dist/translations/bn.js
django_ckeditor_5/static/django_ckeditor_5/dist/translations/bs.js
django_ckeditor_5/static/django_ckeditor_5/dist/translations/ca.js
django_ckeditor_5/static/django_ckeditor_5/dist/translations/cs.js
django_ckeditor_5/static/django_ckeditor_5/dist/translations/da.js
django_ckeditor_5/static/django_ckeditor_5/dist/translations/de-ch.js
django_ckeditor_5/static/django_ckeditor_5/dist/translations/de.js
django_ckeditor_5/static/django_ckeditor_5/dist/translations/el.js
django_ckeditor_5/static/django_ckeditor_5/dist/translations/en-au.js
django_ckeditor_5/static/django_ckeditor_5/dist/translations/en-gb.js
django_ckeditor_5/static/django_ckeditor_5/dist/translations/eo.js
django_ckeditor_5_caravan-0.2.20.dist-info/licenses/LICENSE
django_ckeditor_5_caravan-0.2.20.dist-info/METADATA
django_ckeditor_5_caravan-0.2.20.dist-info/WHEEL
django_ckeditor_5_caravan-0.2.20.dist-info/top_level.txt
django_ckeditor_5_caravan-0.2.20.dist-info/RECORD
