Metadata-Version: 2.4
Name: django-ckeditor-5-caravan
Version: 0.2.20
Summary: CKEditor 5 for Django.
Author-email: Vladislav Khoboko <vladislah@gmail.com>
Maintainer-email: Caravan Coop <hi@caravan.coop>
License: BSD-3-Clause
Project-URL: homepage, https://pypi.org/project/django-ckeditor-5-caravan/
Project-URL: repository, https://github.com/caravancoop/django-ckeditor-5
Keywords: CKEditor,CKEditor5,Django
Classifier: Environment :: Web Environment
Classifier: Framework :: Django
Classifier: Framework :: Django :: 2.2
Classifier: Framework :: Django :: 3.0
Classifier: Framework :: Django :: 4.0
Classifier: Framework :: Django :: 5.0
Classifier: Framework :: Django :: 5.1
Classifier: Intended Audience :: Developers
Classifier: License :: OSI Approved :: BSD License
Classifier: Operating System :: OS Independent
Classifier: Programming Language :: Python
Classifier: Programming Language :: Python :: 3.7
Classifier: Programming Language :: Python :: 3.8
Classifier: Programming Language :: Python :: 3.9
Classifier: Programming Language :: Python :: 3.10
Classifier: Programming Language :: Python :: 3.11
Classifier: Programming Language :: Python :: 3.12
Classifier: Topic :: Internet :: WWW/HTTP
Classifier: Topic :: Internet :: WWW/HTTP :: Dynamic Content
Requires-Python: >=3.7
License-File: LICENSE
Requires-Dist: Django>=2.2
Requires-Dist: Pillow
Provides-Extra: dev
Requires-Dist: bandit[toml]==1.8.2; extra == "dev"
Requires-Dist: black==25.1.0; extra == "dev"
Requires-Dist: codespell==2.4.1; extra == "dev"
Requires-Dist: coverage==7.6.10; extra == "dev"
Requires-Dist: mypy==1.15.0; extra == "dev"
Requires-Dist: mypy-extensions==1.0.0; extra == "dev"
Requires-Dist: pytest==8.3.4; extra == "dev"
Requires-Dist: pytest-cov==6.0.0; extra == "dev"
Requires-Dist: pytest-django==4.9.0; extra == "dev"
Requires-Dist: pytest-mock==3.14.0; extra == "dev"
Requires-Dist: safety==3.2.14; extra == "dev"
Requires-Dist: types-setuptools==75.8.0.20250110; extra == "dev"
Requires-Dist: typing_extensions==4.12.2; extra == "dev"
Dynamic: license-file
